cispliceai/__init__.py
cispliceai/__main__.py
cispliceai/annotation.py
cispliceai/cache.py
cispliceai/console.py
cispliceai/const.py
cispliceai/data.py
cispliceai/fasta.py
cispliceai/model.py
cispliceai/progress.py
cispliceai/data/CI-SpliceAI.pb
cispliceai/data/grch37.csv
cispliceai/data/grch38.csv
cispliceai-1.1.1.dist-info/LICENSE
cispliceai-1.1.1.dist-info/METADATA
cispliceai-1.1.1.dist-info/WHEEL
cispliceai-1.1.1.dist-info/entry_points.txt
cispliceai-1.1.1.dist-info/top_level.txt
cispliceai-1.1.1.dist-info/RECORD
