Metadata-Version: 2.1
Name: cispliceai
Version: 1.1.1
Summary: CI-SpliceAI: Predicting splicing disruptions, trained on all isoforms
Home-page: https://ci-spliceai.com
Author: Yaron Strauch
Author-email: git@yaron-strauch.com
License: CC BY 4.0
Keywords: splicing,rna,machine learning,SpliceAI
License-File: LICENSE
Requires-Dist: keras (<3,>=2.4.0)
Requires-Dist: pyfaidx (>=0.5.0)
Requires-Dist: numpy (>=1)
Requires-Dist: pandas (>=1)
Requires-Dist: pysam (>=0.10)
Provides-Extra: cpu
Requires-Dist: tensorflow (>=1.15.0) ; extra == 'cpu'
Provides-Extra: gpu
Requires-Dist: tensorflow-gpu (>=1.15.0) ; extra == 'gpu'
